{"playlistTitle": "16/21", "playlistAuthor": "megawidget", "image": "", "songs": [{"hash": "5C8135879973BD8E27BA745497FA7D12C6A035E4", "songName": "In My Heart DJMAX", "difficulties": [{"characteristic": "Standard", "name": "Easy"}]}, {"hash": "440C7251532EAD28F661D7DCE5750D3A3E487E7E", "songName": "GAMETIME \u2013 Ninjawekrs Vol. 1 3LAU feat. Ninja", "difficulties": [{"characteristic": "Standard", "name": "Normal"}]}, {"hash": "3F729EE74DB0D1F3807524C99A5D81C0EF81D800", "songName": "Freezer \u2013 Dreamin\u2019 Tonight (ft. Kiichigo)", "difficulties": [{"characteristic": "Standard", "name": "Normal"}]}, {"hash": "2CABD615FE4341A40B175F45F8FC27194D4AFD48", "songName": "Weird Machine (ft. Nevve) (Syrex Nightcore) \u2013 DROELOE", "difficulties": [{"characteristic": "Standard", "name": "Hard"}]}, {"hash": "1E86B21402C5EE98F3DB246F218135B3FF61A21A", "songName": "Shera \u2013 MYUKKE", "difficulties": [{"characteristic": "Standard", "name": "Easy"}]}, {"hash": "998F9B0A3E8B85AD697E8A7AA2C8B7D1F70936CE", "songName": "History Maker \u2013 Dean Fujioka", "difficulties": [{"characteristic": "Standard", "name": "Normal"}]}, {"hash": "F499B0180E081C22ACC8BE0386D01C4C3C4C4368", "songName": "Too Far (ft. Cory Friesenhan) \u2013 Jasted, Foxa & Chester Young", "difficulties": [{"characteristic": "Standard", "name": "Hard"}]}, {"hash": "24F34E47BDFCAE96D1F37117F6F1F4FBE25E58E5", "songName": "Let Mom Sleep (Jet Set Radio) \u2013 Hideki Naganuma", "difficulties": [{"characteristic": "Standard", "name": "Normal"}]}, {"hash": "72705375D53EE75171CD96DE7E5264A3BE8A6D5A", "songName": "Hyouka OP 1 | Yasashisa no Riyuu | Mapped By Ab and Trolav [Criteria Update 4]", "difficulties": [{"characteristic": "Standard", "name": "Expert"}]}, {"hash": "EB28A79E2DBC80948D0EA09631E83557EA6B6735", "songName": "Senbonzakura (Short Ver.) by Kradness + Giga-P", "difficulties": [{"characteristic": "Standard", "name": "Hard"}]}, {"hash": "B3574125C2C8D6E187D4B7C5D59B5BB625FD2217", "songName": "[RANKED] Camellia \u2013 Myths You forgot", "difficulties": [{"characteristic": "Standard", "name": "Expert"}]}, {"hash": "40097F7ED852D6886F6EBCFEEFE42AC2F1AF0958", "songName": "L\u2019Ultima Cena \u2013 Laur [Cytus II]", "difficulties": [{"characteristic": "Standard", "name": "Hard"}]}, {"hash": "E95E6B02DA5D37AF7864637DCA17E1B0D40DBBDB", "songName": "Liberation \u2013 Harold van Lennep", "difficulties": [{"characteristic": "Standard", "name": "ExpertPlus"}]}, {"hash": "727F16F8BEF6DDB62F7A1ABD3677737F5082A302", "songName": "Flat Zone 2 [Smash Bros Map Pack]", "difficulties": [{"characteristic": "Standard", "name": "ExpertPlus"}]}, {"hash": "09F8BEE6908E3A9CD724B3DB3162A5C381ECB156", "songName": "[Ranked] Pegboard Nerds \u2013 Purple People Eater", "difficulties": [{"characteristic": "Standard", "name": "Expert"}]}, {"hash": "580EB7D1614A35D192722F748400C9896AC9527D", "songName": "Darude Sandstorm", "difficulties": [{"characteristic": "Standard", "name": "ExpertPlus"}]}, {"hash": "884E2D9A82F5675DE7C3FA35199EBF24C4F15D23", "songName": "citrus SDVX", "difficulties": [{"characteristic": "Standard", "name": "ExpertPlus"}]}, {"hash": "B3574125C2C8D6E187D4B7C5D59B5BB625FD2217", "songName": "[RANKED] Camellia \u2013 Myths You forgot", "difficulties": [{"characteristic": "Standard", "name": "ExpertPlus"}]}, {"hash": "228B9E3EDC52B7F6B35FE8D47DAFA126E6D62D32", "songName": "Antithese[R]", "difficulties": [{"characteristic": "Standard", "name": "Expert"}]}, {"hash": "B5F2D1D582BE2706E44B860B8A04C7F5F1BE2910", "songName": "Helblinde \u2013 Solace of Oblivion", "difficulties": [{"characteristic": "Standard", "name": "ExpertPlus"}]}, {"hash": "1F2453197F1537DEAD709B6DD0DCB74CAD9B6BE4", "songName": "BABYMETAL \u2013 Distortion", "difficulties": [{"characteristic": "Standard", "name": "Expert"}]}, {"hash": "F99FB53FD30F612E7716898C446984F50BC4C37D", "songName": "M1917 \u2013 a crowd of rebellion", "difficulties": [{"characteristic": "Standard", "name": "ExpertPlus"}]}, {"hash": "8AFB0C840EA4B07DB2A16E96164CE8BE094B2339", "songName": "Kobaryo \u2013 Tool-Assisted Speedcore (TQBF Frame Advance RMX)", "difficulties": [{"characteristic": "Standard", "name": "ExpertPlus"}]}, {"hash": "5868546DD2A98E6F0BC288A83506EB766113A9EB", "songName": "Forever \u2013 Chester Young & STIMX [Chroma]", "difficulties": [{"characteristic": "Standard", "name": "ExpertPlus"}]}, {"hash": "3F97C2436882538C7B482E87A5E97B9F14EDCB69", "songName": "uma vs Morimori Atsushi \u2013 FIRST:DREAMS", "difficulties": [{"characteristic": "Standard", "name": "ExpertPlus"}]}]}